telebirr/__init__.py
telebirr/admin.py
telebirr/apps.py
telebirr/models.py
telebirr/request.py
telebirr/security.py
telebirr/tests.py
telebirr/types.py
telebirr/urls.py
telebirr/views.py
telebirr/migrations/__init__.py
django_telebirr-1.0.1.dist-info/METADATA
django_telebirr-1.0.1.dist-info/WHEEL
django_telebirr-1.0.1.dist-info/top_level.txt
django_telebirr-1.0.1.dist-info/RECORD
